textpression/__init__.py
textpression/cli.py
textpression-0.1.1.dist-info/METADATA
textpression-0.1.1.dist-info/WHEEL
textpression-0.1.1.dist-info/entry_points.txt
textpression-0.1.1.dist-info/top_level.txt
textpression-0.1.1.dist-info/RECORD
