Metadata-Version: 2.1
Name: textpression
Version: 0.1.1
Summary: tools for making expressive unicode text messages
Home-page: https://github.com/rwnx/textpression
Author: Rowan Twell
Author-email: <rowantwell@gmail.com>
Requires-Python: >3.9.0
Requires-Dist: typer[all] >=0.9.0
